{
  "$schema": "http://json-schema.org/draft-04/schema#",
  "type": "object",
  "properties": {
    "RegionName": {
      "type": "string",
      "description": "The unique name of the region within the realm."
    },
    "RegionDescription": {
      "type": "string",
      "description": "A brief description of the region, outlining its distinguishing features or characteristics.",
      "maxLength": 300
    },
    "Geography": {
      "type": "string",
      "description": "Physical description of the region - landforms, bodies of water, climate, etc."
    },
    "NaturalResources": {
      "type": "array",
      "items": {
        "type": "string",
        "description": "Key natural resources found in the region, contributing to its economy or significance."
      }
    },
    "FloraAndFauna": {
      "type": "string",
      "description": "Unique animals, plants, or other organisms native to the region."
    },
    "LocalCulture": {
      "type": "string",
      "description": "Cultural practices unique to the region."
    },
    "DominantSpecies": {
      "type": "string",
      "description": "The species or race which is most prevalent or exerts most influence in this region."
    },
    "HistoricalInfluence": {
      "type": "string",
      "description": "Notable history or events that influence the region's cultural, political or societal norms.",
      "maxLength": 200
    },
    "LocalEconomy": {
      "type": "string",
      "description": "Overview of the region's economic structure and specialization.",
      "maxLength": 150
    },
    "PoliticalInfluence": {
      "type": "string",
      "description": "The role of the region in the overall political landscape of the realm, including local governance.",
      "maxLength": 150
    },
    "MajorSettlements": {
      "type": "array",
      "items": {
        "type": "string",
        "description": "Key cities, towns or other settlements in the region."
      }
    }
  },
  "required": [
    "RegionName",
    "RegionDescription",
    "Geography",
    "NaturalResources",
    "FloraAndFauna",
    "LocalCulture",
    "DominantSpecies",
    "HistoricalInfluence",
    "LocalEconomy",
    "PoliticalInfluence",
    "MajorSettlements"
  ]
}